skteach/__init__.py
scikit_teach-0.1.0.dist-info/LICENSE
scikit_teach-0.1.0.dist-info/METADATA
scikit_teach-0.1.0.dist-info/WHEEL
scikit_teach-0.1.0.dist-info/top_level.txt
scikit_teach-0.1.0.dist-info/RECORD
